cave_agent/__init__.py
cave_agent/agent.py
cave_agent/prompts.py
cave_agent/utils.py
cave_agent/models/__init__.py
cave_agent/models/base.py
cave_agent/models/litellm.py
cave_agent/models/openai.py
cave_agent/parsing/__init__.py
cave_agent/parsing/streaming.py
cave_agent/runtime/__init__.py
cave_agent/runtime/executor.py
cave_agent/runtime/primitives.py
cave_agent/runtime/runtime.py
cave_agent/security/__init__.py
cave_agent/security/checker.py
cave_agent/security/rules.py
cave_agent/skills/__init__.py
cave_agent/skills/constants.py
cave_agent/skills/discovery.py
cave_agent/skills/registry.py
cave_agent/skills/skill.py
cave_agent-0.6.5.dist-info/METADATA
cave_agent-0.6.5.dist-info/WHEEL
cave_agent-0.6.5.dist-info/licenses/LICENSE
cave_agent-0.6.5.dist-info/RECORD
