Metadata-Version: 2.4
Name: cave-agent
Version: 0.6.5
Summary: CaveAgent is a tool-augmented agent framework that enables function-calling through LLM code generation and provides runtime state management. Unlike traditional JSON-schema approaches, it natively handles complex Python objects like DataFrames and ndarrays within a persistent runtime, enabling lossless data flow across multi-turn interactions.
Project-URL: Homepage, https://github.com/acodercat/cave-agent
Project-URL: Repository, https://github.com/acodercat/cave-agent
Author-email: Ram <codermao@gmail.com>
License-File: LICENSE
Keywords: agent,function-calling,llm,tool-calling
Classifier: Development Status :: 3 - Alpha
Classifier: Intended Audience :: Developers
Classifier: License :: OSI Approved :: MIT License
Classifier: Programming Language :: Python :: 3.11
Classifier: Programming Language :: Python :: 3.12
Classifier: Topic :: Software Development :: Libraries :: Python Modules
Requires-Python: >=3.11
Requires-Dist: ipython>=9.7.0
Requires-Dist: pydantic>=2.12.4
Requires-Dist: pyyaml>=6.0.3
Requires-Dist: rich>=13.9.4
Provides-Extra: all
Requires-Dist: litellm>=1.80.5; extra == 'all'
Requires-Dist: openai>=2.8.1; extra == 'all'
Provides-Extra: litellm
Requires-Dist: litellm>=1.80.5; extra == 'litellm'
Provides-Extra: openai
Requires-Dist: openai>=2.8.1; extra == 'openai'
